Metadata-Version: 2.1
Name: AC12066UNO
Version: 0.1.0
Summary: Una librería para resolver sistemas de ecuaciones lineales y no lineales en Python.
Home-page: https://github.com/ale-0293/AC12066UNO
Author: Martín
Author-email: martin.a.ac@outlook.com
Classifier: Programming Language :: Python :: 3
Classifier: License :: OSI Approved :: MIT License
Classifier: Operating System :: OS Independent
Classifier: Intended Audience :: Education
Classifier: Topic :: Scientific/Engineering :: Mathematics
Requires-Python: >=3.8
License-File: LICENSE
